<?xml version="1.0" encoding="UTF-8"?>
<Monument xmlns:xsi="http://www.w3.org/2001/XMLSchema-instance" 
xsi:noNamespaceSchemaLocation="../src/main/resources/templates/Monument.xsd">
   <id>280</id>
   <nom>Yasmine Overland</nom>
   <description>Tetouan Morocco</description>
   <coordinate>
      <latitude>35.59244</latitude>
      <longitude>-5.3395</longitude>
   </coordinate>
   <liensImage>
      <liensImage>https://media-cdn.tripadvisor.com/media/photo-o/1a/1a/a6/54/our-fleet.jpg</liensImage>
   </liensImage>
   <ville>
      <nom>Tetouan</nom>
      <description>Tetouan</description>
   </ville>
   <evaluations/>
   <rating>5.0</rating>
</Monument>